smdb_logger/__init__.py
smdb_logger-0.7.0.dist-info/licenses/LICENSE
smdb_logger-0.7.0.dist-info/METADATA
smdb_logger-0.7.0.dist-info/WHEEL
smdb_logger-0.7.0.dist-info/top_level.txt
smdb_logger-0.7.0.dist-info/RECORD
