Metadata-Version: 2.4
Name: smdb_logger
Version: 0.7.0
Summary: Logger used by Server Monitoring Discord Bot and all extentions made by me
Home-page: https://github.com/NightKey/smdb-logger
Author: Janthó Dávid
Author-email: davidjantho@gmail.com
Project-URL: Bug Tracker, https://github.com/NightKey/smdb-logger/issues
Classifier: Development Status :: 4 - Beta
Classifier: Programming Language :: Python :: 3
Classifier: License :: Freeware
Classifier: Operating System :: OS Independent
Requires-Python: >=3.7
License-File: LICENSE
Dynamic: license-file
